hid_watchdog/__init__.py
hid_watchdog/cli.py
hid_watchdog/hid_watchdog.py
hid_watchdog-0.1.7.dist-info/AUTHORS.rst
hid_watchdog-0.1.7.dist-info/LICENSE
hid_watchdog-0.1.7.dist-info/METADATA
hid_watchdog-0.1.7.dist-info/WHEEL
hid_watchdog-0.1.7.dist-info/entry_points.txt
hid_watchdog-0.1.7.dist-info/top_level.txt
hid_watchdog-0.1.7.dist-info/RECORD
