Metadata-Version: 2.1
Name: hid-watchdog
Version: 0.1.7
Summary: Service to talk to cheap USB-HID Watchdog Timers
Home-page: https://github.com/technotaff/hid_watchdog
Author: Steve Randall
Author-email: steve@mylastname.cc
License: GNU General Public License v3
Keywords: hid_watchdog
Platform: UNKNOWN
Classifier: Development Status :: 2 - Pre-Alpha
Classifier: Intended Audience :: Developers
Classifier: License :: OSI Approved :: GNU General Public License v3 (GPLv3)
Classifier: Natural Language :: English
Classifier: Programming Language :: Python :: 3
Classifier: Programming Language :: Python :: 3.6
Classifier: Programming Language :: Python :: 3.7
Classifier: Programming Language :: Python :: 3.8
Requires-Python: ~=3.6
Requires-Dist: hid
